{
    "form": {
        "attachments": {
            "label": "المرفقات",
            "placeholder": "إضافة ملف(ملفات)"
        },
        "buttonText": "اتصل بنا",
        "email": {
            "label": "البريد الإلكتروني",
            "placeholder": "البريد الإلكتروني"
        },
        "message": {
            "label": "اكتب رسالتك هنا...",
            "placeholder": "اكتب رسالتك هنا..."
        },
        "name": {
            "label": "الاسم",
            "placeholder": "الاسم"
        },
        "submit": "إرسال نموذج الاتصال",
        "website": {
            "label": "الموقع الإلكتروني",
            "placeholder": "الموقع الإلكتروني"
        }
    },
    "metadata": {
        "description": "تواصل مع mshrm.studio. تواصل معنا عبر النموذج الخاص بنا، واعثر على مواقعنا وأرقام الهواتف والبريد الإلكتروني للاستفسارات. نقدم حلولًا مبتكرة للبرامج والتطبيقات وحلول تكنولوجيا المعلومات عالميًا.",
        "title": "اتصل بـ mshrm.studio | تواصل للحصول على حلول البرمجيات والتطبيقات وتكنولوجيا المعلومات"
    }
}
